tether/__init__.py
tether/camera.py
tether/constants.py
tether/ptp.py
tether/test.py
pylumixtether-0.0.1.dist-info/LICENSE
pylumixtether-0.0.1.dist-info/METADATA
pylumixtether-0.0.1.dist-info/WHEEL
pylumixtether-0.0.1.dist-info/top_level.txt
pylumixtether-0.0.1.dist-info/RECORD
